factern_client/__init__.py
factern_client/api_client.py
factern_client/configuration.py
factern_client/rest.py
factern_client/com/__init__.py
factern_client/com/factern/__init__.py
factern_client/com/factern/api/__init__.py
factern_client/com/factern/api/facts_api.py
factern_client/com/factern/model/__init__.py
factern_client/com/factern/model/account.py
factern_client/com/factern/model/add_label_request.py
factern_client/com/factern/model/add_label_response.py
factern_client/com/factern/model/add_statement_request.py
factern_client/com/factern/model/add_statement_response.py
factern_client/com/factern/model/agent.py
factern_client/com/factern/model/alias.py
factern_client/com/factern/model/alias_node.py
factern_client/com/factern/model/api_endpoint.py
factern_client/com/factern/model/application.py
factern_client/com/factern/model/application_node.py
factern_client/com/factern/model/base_request.py
factern_client/com/factern/model/base_response.py
factern_client/com/factern/model/bid.py
factern_client/com/factern/model/bid_node.py
factern_client/com/factern/model/cost.py
factern_client/com/factern/model/create_alias_request.py
factern_client/com/factern/model/create_alias_response.py
factern_client/com/factern/model/create_application_request.py
factern_client/com/factern/model/create_application_response.py
factern_client/com/factern/model/create_bid_request.py
factern_client/com/factern/model/create_bid_response.py
factern_client/com/factern/model/create_child_request.py
factern_client/com/factern/model/create_domain_request.py
factern_client/com/factern/model/create_domain_response.py
factern_client/com/factern/model/create_entity_request.py
factern_client/com/factern/model/create_entity_response.py
factern_client/com/factern/model/create_field_request.py
factern_client/com/factern/model/create_field_response.py
factern_client/com/factern/model/create_filter_request.py
factern_client-1.0.0.dist-info/METADATA
factern_client-1.0.0.dist-info/RECORD
factern_client-1.0.0.dist-info/WHEEL
factern_client-1.0.0.dist-info/top_level.txt
